CHANGES.txt
MANIFEST.in
README.md
setup.py
ops/__init__.py
ops/api.py
ops/compound.py
ops/target.py
ops.py.egg-info/PKG-INFO
ops.py.egg-info/SOURCES.txt
ops.py.egg-info/dependency_links.txt
ops.py.egg-info/top_level.txt
ops/test/__init__.py
ops/test/tests.py