Metadata-Version: 1.1
Name: ops.py
Version: 0.1.0a2
Summary: Python Library for the Open PHACTS Platform API
Home-page: https://github.com/pgroth/ops.py
Author: Paul Groth
Author-email: p.t.groth@vu.nl
License: Apache 2.0
Keywords: api data integration,database,drug discovery
Platform: UNKNOWN
Classifier: Development Status :: 2 - Pre-Alpha
Classifier: Intended Audience :: Developers
Classifier: Intended Audience :: Science/Research
Classifier: License :: OSI Approved :: Apache Software License
Classifier: Operating System :: OS Independent
Classifier: Programming Language :: Python :: 2.7
Classifier: Topic :: Scientific/Engineering :: Chemistry
Classifier: Topic :: Scientific/Engineering :: Bio-Informatics
